pybombs/__init__.py
pybombs/config_file.py
pybombs/config_manager.py
pybombs/dep_manager.py
pybombs/fetcher.py
pybombs/gitcache_manager.py
pybombs/install_manager.py
pybombs/inventory.py
pybombs/main.py
pybombs/package_manager.py
pybombs/pb_exception.py
pybombs/pb_logging.py
pybombs/recipe.py
pybombs/recipe_manager.py
pybombs/requirer.py
pybombs/tree_node.py
pybombs/commands/__init__.py
pybombs/commands/autoconfig.py
pybombs/commands/base.py
pybombs/commands/config.py
pybombs/commands/deploy.py
pybombs/commands/digraph.py
pybombs/commands/fetch.py
pybombs/commands/git.py
pybombs/commands/help.py
pybombs/commands/install.py
pybombs/commands/inv.py
pybombs/commands/lint.py
pybombs/commands/prefix.py
pybombs/commands/rebuild.py
pybombs/commands/recipes.py
pybombs/commands/remove.py
pybombs/commands/run.py
pybombs/fetchers/__init__.py
pybombs/fetchers/base.py
pybombs/fetchers/file.py
pybombs/fetchers/git.py
pybombs/fetchers/svn.py
pybombs/fetchers/wget.py
pybombs/packagers/__init__.py
pybombs/packagers/apt.py
pybombs/packagers/base.py
pybombs/packagers/brew.py
pybombs/packagers/cmd.py
pybombs/packagers/dummy.py
pybombs/packagers/extern.py
pybombs/packagers/pacman.py
pybombs/packagers/pip.py
pybombs/packagers/pkgconfig.py
pybombs/packagers/port.py
pybombs/packagers/portage.py
pybombs/packagers/pymod.py
pybombs/packagers/source.py
pybombs/packagers/yum.py
pybombs/packagers/zypper.py
pybombs/recipes/autoconf.lwr
pybombs/recipes/automake.lwr
pybombs/recipes/autotools-bootstrap.lwr
pybombs/recipes/build-essential.lwr
pybombs/recipes/cmake.lwr
pybombs/recipes/default_prefix.lwr
pybombs/recipes/git.lwr
pybombs/recipes/graphviz.lwr
pybombs/recipes/python-requests.lwr
pybombs/recipes/python.lwr
pybombs/recipes/xz.lwr
pybombs/templates/autoconf.lwt
pybombs/templates/bjam.lwt
pybombs/templates/boostflags.lwt
pybombs/templates/bootstrapautoconf.lwt
pybombs/templates/cmake.lwt
pybombs/templates/distutils.lwt
pybombs/templates/empty.lwt
pybombs/templates/prefix.lwt
PyBOMBS-2.3.5.dist-info/AUTHORS
PyBOMBS-2.3.5.dist-info/COPYING
PyBOMBS-2.3.5.dist-info/METADATA
PyBOMBS-2.3.5.dist-info/WHEEL
PyBOMBS-2.3.5.dist-info/entry_points.txt
PyBOMBS-2.3.5.dist-info/top_level.txt
PyBOMBS-2.3.5.dist-info/RECORD
