Metadata-Version: 2.1
Name: PyBOMBS
Version: 2.3.5
Summary: A meta-package manager to install software from source, or whatever the local package manager is. Designed for easy install of source trees for the GNU Radio project.
Home-page: https://www.gnuradio.org/blog/pybombs-the-what-the-how-and-the-why/
Author: Martin Braun
Author-email: martin@gnuradio.org
Maintainer: Martin Braun
Maintainer-email: martin@gnuradio.org
License: GPLv3
Download-URL: https://github.com/gnuradio/pybombs/tarball/v2.3.5
Platform: UNKNOWN
Classifier: Development Status :: 4 - Beta
Classifier: Environment :: Console
Classifier: Intended Audience :: System Administrators
Classifier: Intended Audience :: Telecommunications Industry
Classifier: License :: OSI Approved :: GNU General Public License v3 (GPLv3)
Classifier: Operating System :: POSIX
Classifier: Programming Language :: Python :: 2.7
Classifier: Topic :: Communications :: Ham Radio
Classifier: Topic :: Software Development :: Build Tools
Classifier: Topic :: Software Development :: Embedded Systems
Classifier: Topic :: System :: Archiving :: Packaging
Classifier: Topic :: System :: Installation/Setup
Classifier: Topic :: System :: Software Distribution
Classifier: Topic :: Utilities
Requires-Dist: setuptools
Requires-Dist: requests
Requires-Dist: six
Requires-Dist: future
Requires-Dist: ruamel.yaml (>=0.15.0)
